neurovoc/__init__.py
neurovoc/cli.py
neurovoc/generate.py
neurovoc/neurogram.py
neurovoc/plotting.py
neurovoc/reconstruct.py
neurovoc-0.1.1.dist-info/licenses/LICENSE
neurovoc-0.1.1.dist-info/METADATA
neurovoc-0.1.1.dist-info/WHEEL
neurovoc-0.1.1.dist-info/entry_points.txt
neurovoc-0.1.1.dist-info/top_level.txt
neurovoc-0.1.1.dist-info/RECORD
