Metadata-Version: 2.4
Name: neurovoc
Version: 0.1.1
Summary: A biologically plausible vocoder framework for auditory perception modeling and cochlear implant simulation
Author-email: Jacob de Nobel <jacobdenobel@gmail.com>
License-Expression: MIT
Project-URL: Homepage, https://github.com/jacobdenobel/neurovoc
Project-URL: Repository, https://github.com/jacobdenobel/neurovoc
Classifier: Programming Language :: Python :: 3
Classifier: Operating System :: OS Independent
Classifier: Topic :: Scientific/Engineering
Classifier: Intended Audience :: Science/Research
Requires-Python: >=3.7
License-File: LICENSE
Requires-Dist: numpy
Requires-Dist: librosa
Requires-Dist: scipy
Requires-Dist: matplotlib
Requires-Dist: brucezilany
Requires-Dist: phastc
Requires-Dist: black
Requires-Dist: click
Requires-Dist: pandas
Requires-Dist: fastdtw
Requires-Dist: tqdm
Dynamic: license-file
